.DS_Store
.gitattributes
.gitignore
.readthedocs.yaml
LICENSE
README.rst
requirements.txt
setup.cfg
setup.py
.github/workflows/release_pypi.yml
.vscode/launch.json
.vscode/settings.json
docs/Makefile
docs/conf.py
docs/index.rst
docs/requirements-build-docs.txt
neuroimagingtools.egg-info/PKG-INFO
neuroimagingtools.egg-info/SOURCES.txt
neuroimagingtools.egg-info/dependency_links.txt
neuroimagingtools.egg-info/requires.txt
neuroimagingtools.egg-info/top_level.txt
nitools/__init__.py
nitools/border.py
nitools/cifti.py
nitools/color.py
nitools/gifti.py
nitools/spm.py
nitools/volume.py
tests/bezier_test.ipynb
tests/border_test.py
tests/cifti_test.py
tests/gifti_test.py
tests/test_spm.py
tests/volume_test.py
tests/wm_test.py