Metadata-Version: 2.1
Name: neuroimagingtools
Version: 1.1.5
Summary: Neuroimaging analysis tools
Home-page: https://github.com/DiedrichsenLab/nitools
Download-URL: https://github.com/DiedrichsenLab/nitools/archive/refs/tags/v1.1.5.tar.gz
Author: Jörn Diedrichsen
Author-email: joern.diedrichsen@googlemail.com
License: MIT
Keywords: imaging analysis,nifti,gifti,cifti
Classifier: Development Status :: 4 - Beta
Classifier: Intended Audience :: Science/Research
Classifier: Intended Audience :: Developers
Classifier: Topic :: Software Development :: Build Tools
Classifier: License :: OSI Approved :: MIT License
Classifier: Programming Language :: Python :: 3.6
Classifier: Programming Language :: Python :: 3.7
Classifier: Programming Language :: Python :: 3.8
Classifier: Programming Language :: Python :: 3.9
Requires-Python: >=3.6
License-File: LICENSE
Requires-Dist: numpy>=1.20.1
Requires-Dist: matplotlib>=3.4.3
Requires-Dist: nibabel>=4.0.2
Requires-Dist: pandas>=1.3.2
